nameattr/__init__.py
nameattr/_match.py
nameattr/_text.py
nameattr/_type.py
nameattr-1.0.0.dist-info/LICENSE
nameattr-1.0.0.dist-info/METADATA
nameattr-1.0.0.dist-info/WHEEL
nameattr-1.0.0.dist-info/top_level.txt
nameattr-1.0.0.dist-info/RECORD
